metprint/__init__.py
metprint-2021.dist-info/LICENSE.md
metprint-2021.dist-info/WHEEL
metprint-2021.dist-info/METADATA
metprint-2021.dist-info/RECORD
