Metadata-Version: 2.1
Name: metprint
Version: 2021
Summary: Pretty print text in a range of builtin formats or make your own
Home-page: https://github.com/FHPythonUtils/MetPrint
License: MIT
Author: FredHappyface
Requires-Python: >=3.7,<4.0
Classifier: Development Status :: 5 - Production/Stable
Classifier: Environment :: Console
Classifier: Intended Audience :: Developers
Classifier: Intended Audience :: Education
Classifier: License :: OSI Approved :: MIT License
Classifier: Natural Language :: English
Classifier: Operating System :: OS Independent
Classifier: Programming Language :: Python :: 3
Classifier: Programming Language :: Python :: 3.10
Classifier: Programming Language :: Python :: 3.7
Classifier: Programming Language :: Python :: 3.8
Classifier: Programming Language :: Python :: 3.9
Classifier: Programming Language :: Python :: Implementation :: CPython
Classifier: Topic :: Multimedia :: Graphics
Classifier: Topic :: Software Development :: Libraries :: Python Modules
Classifier: Topic :: Utilities
Project-URL: Documentation, https://github.com/FHPythonUtils/MetPrint/blob/master/README.md
Project-URL: Repository, https://github.com/FHPythonUtils/MetPrint
